at_common_workflow/__init__.py
at_common_workflow/core/__init__.py
at_common_workflow/core/constants.py
at_common_workflow/core/context.py
at_common_workflow/core/exceptions.py
at_common_workflow/core/task/__init__.py
at_common_workflow/core/task/base.py
at_common_workflow/core/task/builder.py
at_common_workflow/core/task/definition.py
at_common_workflow/core/task/processing_task.py
at_common_workflow/core/task/validation.py
at_common_workflow/core/workflow/__init__.py
at_common_workflow/core/workflow/base.py
at_common_workflow/core/workflow/builder.py
at_common_workflow/core/workflow/node.py
at_common_workflow/core/workflow/execution/events.py
at_common_workflow/core/workflow/execution/executor.py
at_common_workflow/core/workflow/execution/progress.py
at_common_workflow/core/workflow/graph/__init__.py
at_common_workflow/core/workflow/graph/dependency.py
at_common_workflow/core/workflow/graph/dependency_adapter.py
at_common_workflow/core/workflow/graph/dependency_graph.py
at_common_workflow/utils/__init__.py
at_common_workflow/utils/logging.py
at_common_workflow/utils/mappings.py
at_common_workflow-1.5.8.dist-info/licenses/LICENSE
at_common_workflow-1.5.8.dist-info/METADATA
at_common_workflow-1.5.8.dist-info/WHEEL
at_common_workflow-1.5.8.dist-info/top_level.txt
at_common_workflow-1.5.8.dist-info/RECORD
