Metadata-Version: 2.4
Name: at_common_workflow
Version: 1.5.8
Summary: A robust Python package for building and executing asynchronous workflow tasks in a directed acyclic graph (DAG) pattern. This package provides a type-safe, thread-safe framework for defining, organizing, and running dependent tasks with comprehensive validation and error handling.
Author-email: Rui Chen <apextrader.ai@gmail.com>
Project-URL: Homepage, https://github.com/apex-trader/at-common-workflow
Project-URL: Bug Tracker, https://github.com/apex-trader/at-common-workflow/issues
Classifier: Programming Language :: Python :: 3
Classifier: License :: OSI Approved :: MIT License
Classifier: Operating System :: OS Independent
Requires-Python: >=3.11
License-File: LICENSE
Requires-Dist: pydantic>=2.10.6
Requires-Dist: typing_extensions>=4.12.2
Provides-Extra: dev
Requires-Dist: pytest>=8.3.4; extra == "dev"
Requires-Dist: pytest-asyncio>=0.25.3; extra == "dev"
Dynamic: license-file
